prism_rofi/__init__.py
prism_rofi/__main__.py
prism_rofi/icons/__init__.py
prism_rofi/icons/fabric.png
prism_rofi/icons/forge.png
prism_rofi/icons/grass.png
prism_rofi/icons/neoforge.png
prism_rofi/icons/quilt.png
prism_rofi-0.7.0.dist-info/METADATA
prism_rofi-0.7.0.dist-info/WHEEL
prism_rofi-0.7.0.dist-info/entry_points.txt
prism_rofi-0.7.0.dist-info/RECORD
