Metadata-Version: 2.1
Name: prism-rofi
Version: 0.7.0
Summary: Prism Launcher shim for Rofi
License: GPL-3.0-or-later
Author: Lura Skye
Author-email: l@veriny.tf
Requires-Python: >=3.11
Classifier: License :: OSI Approved :: GNU General Public License v3 or later (GPLv3+)
Classifier: Programming Language :: Python :: 3
Classifier: Programming Language :: Python :: 3.11
Classifier: Programming Language :: Python :: 3.12
